src/comb_curcuit.v
module comb_two(a,b,c,d,f);
    input a,b,c,d;
    output f;
    wire t1,t2;
    assign t1 = a&b;
    assign t2 = ~(c|d);
    assign f = ~(t1&t2);

endmodule

testBench/comb_curcuit_tb.v
`timescale 1ns/1ps

module comb_two_tb;

    reg a;
    reg b;
    reg c;
    reg d;
    wire f;

    // Instantiate the Unit Under Test (UUT)
    comb_two uut (
        .a(a),
        .b(b),
        .c(c),
        .d(d),
        .f(f)
    );

    initial begin
        // Initialize VCD dump
        $dumpfile("vcd/comb_curcuit.vcd");
        $dumpvars(0, comb_two_tb);

        // Initialize inputs
        a = 0;
        b = 0;
        c = 0;
        d = 0;

        // Test cases
        #10;
        a = 0;
        b = 0;
        c = 0;
        d = 0;
        #10;
        $display("Time=%0t: a=%b b=%b c=%b d=%b f=%b ", $time, a, b, c, d, f);

        #10;
        a = 1;
        b = 0;
        c = 0;
        d = 0;
        #10;
        $display("Time=%0t: a=%b b=%b c=%b d=%b f=%b ", $time, a, b, c, d, f);

        #10;
        a = 0;
        b = 1;
        c = 0;
        d = 0;
        #10;
        $display("Time=%0t: a=%b b=%b c=%b d=%b f=%b ", $time, a, b, c, d, f);

        #10;
        a = 1;
        b = 1;
        c = 0;
        d = 0;
        #10;
        $display("Time=%0t: a=%b b=%b c=%b d=%b f=%b ", $time, a, b, c, d, f);

        #10;
        a = 0;
        b = 0;
        c = 1;
        d = 0;
        #10;
        $display("Time=%0t: a=%b b=%b c=%b d=%b f=%b ", $time, a, b, c, d, f);

        #10;
        a = 1;
        b = 0;
        c = 1;
        d = 0;
        #10;
        $display("Time=%0t: a=%b b=%b c=%b d=%b f=%b ", $time, a, b, c, d, f);

        #10;
        a = 0;
        b = 1;
        c = 1;
        d = 0;
        #10;
        $display("Time=%0t: a=%b b=%b c=%b d=%b f=%b ", $time, a, b, c, d, f);

        #10;
        a = 1;
        b = 1;
        c = 1;
        d = 0;
        #10;
        $display("Time=%0t: a=%b b=%b c=%b d=%b f=%b ", $time, a, b, c, d, f);

        #10;
        a = 0;
        b = 0;
        c = 0;
        d = 1;
        #10;
        $display("Time=%0t: a=%b b=%b c=%b d=%b f=%b ", $time, a, b, c, d, f);

        #10;
        a = 1;
        b = 0;
        c = 0;
        d = 1;
        #10;
        $display("Time=%0t: a=%b b=%b c=%b d=%b f=%b ", $time, a, b, c, d, f);

        #10;
        a = 0;
        b = 1;
        c = 0;
        d = 1;
        #10;
        $display("Time=%0t: a=%b b=%b c=%b d=%b f=%b ", $time, a, b, c, d, f);

        #10;
        a = 1;
        b = 1;
        c = 0;
        d = 1;
        #10;
        $display("Time=%0t: a=%b b=%b c=%b d=%b f=%b ", $time, a, b, c, d, f);

        #10;
        a = 0;
        b = 0;
        c = 1;
        d = 1;
        #10;
        $display("Time=%0t: a=%b b=%b c=%b d=%b f=%b ", $time, a, b, c, d, f);

        #10;
        a = 1;
        b = 0;
        c = 1;
        d = 1;
        #10;
        $display("Time=%0t: a=%b b=%b c=%b d=%b f=%b ", $time, a, b, c, d, f);

        #10;
        a = 0;
        b = 1;
        c = 1;
        d = 1;
        #10;
        $display("Time=%0t: a=%b b=%b c=%b d=%b f=%b ", $time, a, b, c, d, f);

        #10;
        a = 1;
        b = 1;
        c = 1;
        d = 1;
        #10;
        $display("Time=%0t: a=%b b=%b c=%b d=%b f=%b ", $time, a, b, c, d, f);

        #10;
        $finish;
    end

endmodule

vcd/comb_curcuit.vcd
$date
	Tue Jun 03 22:13:21 2025
$end
$version
	Icarus Verilog
$end
$timescale
	1ps
$end
$scope module comb_two_tb $end
$var wire 1 ! f $end
$var reg 1 " a $end
$var reg 1 # b $end
$var reg 1 $ c $end
$var reg 1 % d $end
$scope module uut $end
$var wire 1 " a $end
$var wire 1 # b $end
$var wire 1 $ c $end
$var wire 1 % d $end
$var wire 1 ! f $end
$var wire 1 & t1 $end
$var wire 1 ' t2 $end
$upscope $end
$upscope $end
$enddefinitions $end
$comment Show the parameter values. $end
$dumpall
$end
#0
$dumpvars
1'
0&
0%
0$
0#
0"
1!
$end
#30000
1"
#50000
1#
0"
#70000
0!
1&
1"
#90000
1!
0'
0&
1$
0#
0"
#110000
1"
#130000
1#
0"
#150000
1&
1"
#170000
0&
1%
0$
0#
0"
#190000
1"
#210000
1#
0"
#230000
1&
1"
#250000
0&
1$
0#
0"
#270000
1"
#290000
1#
0"
#310000
1&
1"
